deluge_web_client/__init__.py
deluge_web_client/client.py
deluge_web_client/exceptions.py
deluge_web_client/py.typed
deluge_web_client/schema.py
deluge_web_client/state.py
deluge_web_client-2.0.3.dist-info/licenses/LICENSE
deluge_web_client-2.0.3.dist-info/METADATA
deluge_web_client-2.0.3.dist-info/WHEEL
deluge_web_client-2.0.3.dist-info/top_level.txt
deluge_web_client-2.0.3.dist-info/RECORD
