Metadata-Version: 2.4
Name: deluge-web-client
Version: 2.0.3
Summary: Deluge Web Client
Author: jessielw
License: Copyright 2025 Jessie Wilson
Project-URL: Homepage, https://github.com/jessielw/deluge-web-client
Project-URL: Documentation, https://deluge-web-client.readthedocs.io
Project-URL: Source, https://github.com/jessielw/deluge-web-client
Keywords: python,deluge,api,client,torrent,torrents,webui,web,rpc,core
Classifier: License :: OSI Approved :: MIT License
Classifier: Development Status :: 5 - Production/Stable
Classifier: Intended Audience :: Developers
Classifier: Operating System :: OS Independent
Classifier: Environment :: Console
Classifier: Programming Language :: Python :: 3
Classifier: Programming Language :: Python :: 3 :: Only
Classifier: Programming Language :: Python :: 3.9
Classifier: Programming Language :: Python :: 3.10
Classifier: Programming Language :: Python :: 3.11
Classifier: Programming Language :: Python :: 3.12
Classifier: Programming Language :: Python :: 3.13
Classifier: Programming Language :: Python :: 3.14
Classifier: Programming Language :: Python :: Implementation :: CPython
Classifier: Topic :: Utilities
Classifier: Topic :: Communications :: File Sharing
Classifier: Typing :: Typed
Requires-Python: <3.15,>=3.9
License-File: LICENSE
Requires-Dist: niquests>=3.15.2
Dynamic: license-file
